cobinhood-0.1.0.dist-info/METADATA
cobinhood-0.1.0.dist-info/RECORD
cobinhood-0.1.0.dist-info/WHEEL
cobinhood-0.1.0.dist-info/top_level.txt
cobinhood_api/__init__.py
cobinhood_api/common.py
cobinhood_api/configuration.py
cobinhood_api/http/__init__.py
cobinhood_api/http/chart.py
cobinhood_api/http/market.py
cobinhood_api/http/system.py
cobinhood_api/http/trading.py
cobinhood_api/http/wallet.py
cobinhood_api/ws/__init__.py
cobinhood_api/ws/feed.py
cobinhood_api/ws/response.py
cobinhood_api/ws/subscribe.py
